helloworld_laurelrr.py
helloworld_laurelrr-0.0.2.dist-info/LICENSE.txt
helloworld_laurelrr-0.0.2.dist-info/METADATA
helloworld_laurelrr-0.0.2.dist-info/WHEEL
helloworld_laurelrr-0.0.2.dist-info/top_level.txt
helloworld_laurelrr-0.0.2.dist-info/RECORD
