Metadata-Version: 2.1
Name: helloworld-laurelrr
Version: 0.0.2
Summary: Say hello!
Home-page: https://github.com/laurelrr/helloworld_laurelrr
Author: Laurel Keyes
Author-email: laurelrr@gmail.com
License: UNKNOWN
Platform: UNKNOWN
Classifier: Programming Language :: Python :: 3
Classifier: Programming Language :: Python :: 3.6
Classifier: Programming Language :: Python :: 3.7
Classifier: License :: OSI Approved :: MIT License
Classifier: Operating System :: OS Independent
Provides-Extra: dev
Requires-Dist: pytest (>3.3) ; extra == 'dev'
